AUTHORS.rst
CONTRIBUTING.rst
HISTORY.rst
LICENSE
MANIFEST.in
README.rst
setup.cfg
setup.py
django_slds_crispyforms/__init__.py
django_slds_crispyforms.egg-info/PKG-INFO
django_slds_crispyforms.egg-info/SOURCES.txt
django_slds_crispyforms.egg-info/dependency_links.txt
django_slds_crispyforms.egg-info/not-zip-safe
django_slds_crispyforms.egg-info/top_level.txt
django_slds_crispyforms/templates/crispy_slds/accordion-group.html
django_slds_crispyforms/templates/crispy_slds/accordion.html
django_slds_crispyforms/templates/crispy_slds/betterform.html
django_slds_crispyforms/templates/crispy_slds/display_form.html
django_slds_crispyforms/templates/crispy_slds/errors.html
django_slds_crispyforms/templates/crispy_slds/errors_formset.html
django_slds_crispyforms/templates/crispy_slds/field.html
django_slds_crispyforms/templates/crispy_slds/table_inline_formset.html
django_slds_crispyforms/templates/crispy_slds/uni_form.html
django_slds_crispyforms/templates/crispy_slds/uni_formset.html
django_slds_crispyforms/templates/crispy_slds/whole_uni_form.html
django_slds_crispyforms/templates/crispy_slds/whole_uni_formset.html
django_slds_crispyforms/templates/crispy_slds/layout/alert.html
django_slds_crispyforms/templates/crispy_slds/layout/baseinput.html
django_slds_crispyforms/templates/crispy_slds/layout/button.html
django_slds_crispyforms/templates/crispy_slds/layout/checkboxselectmultiple.html
django_slds_crispyforms/templates/crispy_slds/layout/checkboxselectmultiple_inline.html
django_slds_crispyforms/templates/crispy_slds/layout/field_errors.html
django_slds_crispyforms/templates/crispy_slds/layout/field_errors_block.html
django_slds_crispyforms/templates/crispy_slds/layout/field_with_buttons.html
django_slds_crispyforms/templates/crispy_slds/layout/formactions.html
django_slds_crispyforms/templates/crispy_slds/layout/help_text.html
django_slds_crispyforms/templates/crispy_slds/layout/help_text_and_errors.html
django_slds_crispyforms/templates/crispy_slds/layout/multifield.html
django_slds_crispyforms/templates/crispy_slds/layout/prepended_appended_text.html
django_slds_crispyforms/templates/crispy_slds/layout/radioselect.html
django_slds_crispyforms/templates/crispy_slds/layout/radioselect_inline.html
