Metadata-Version: 1.1
Name: django-slds-crispyforms
Version: 0.1.0
Summary: Django Crispy Forms template overrides for rendering forms using the Salesforce Lightning Design System
Home-page: https://github.com/SalesforceFoundation/django-slds-crispyforms
Author: Jason Lantz
Author-email: jlantz@salesforce.com
License: BSD
Keywords: django-slds-crispyforms
Platform: UNKNOWN
Classifier: Development Status :: 3 - Alpha
Classifier: Framework :: Django
Classifier: Framework :: Django :: 1.8
Classifier: Framework :: Django :: 1.9
Classifier: Framework :: Django :: 1.10
Classifier: Intended Audience :: Developers
Classifier: License :: OSI Approved :: BSD License
Classifier: Natural Language :: English
Classifier: Programming Language :: Python :: 2
Classifier: Programming Language :: Python :: 2.7
Classifier: Programming Language :: Python :: 3
Classifier: Programming Language :: Python :: 3.2
Classifier: Programming Language :: Python :: 3.3
Classifier: Programming Language :: Python :: 3.4
Classifier: Programming Language :: Python :: 3.5
